treetable.py
treetable-0.1.dist-info/LICENSE
treetable-0.1.dist-info/METADATA
treetable-0.1.dist-info/WHEEL
treetable-0.1.dist-info/top_level.txt
treetable-0.1.dist-info/RECORD
